cryptopian_infra/__init__.py
cryptopian_infra/sendalert.py
cryptopian_infra/alert/__init__.py
cryptopian_infra/alert/alert.py
cryptopian_infra/alert/alertwrapper.py
cryptopian_infra/alert/feishuwebhook.py
cryptopian_infra/alert/slackwebhook.py
cryptopian_infra/config/__init__.py
cryptopian_infra/config/apimanager.py
cryptopian_infra/config/configloader.py
cryptopian_infra/config/influxdb2factory.py
cryptopian_infra/config/influxdbfactory.py
cryptopian_infra/config/mongofactory.py
cryptopian_infra/config/secretmanagerbase.py
cryptopian_infra/config/slackwebhookfactory.py
cryptopian_infra/infra/__init__.py
cryptopian_infra/infra/duration.py
cryptopian_infra/infra/emailclient.py
cryptopian_infra/infra/gracefullystopdocker.py
cryptopian_infra/infra/stopwatch.py
cryptopian_infra/mongo/__init__.py
cryptopian_infra/mongo/mongoparameters.py
cryptopian_infra/threading/__init__.py
cryptopian_infra/threading/atomicaccstore.py
cryptopian_infra/threading/messagepump.py
cryptopian_infra/utils/__init__.py
cryptopian_infra/utils/asyncutils.py
cryptopian_infra/utils/datetimeutils.py
cryptopian_infra/utils/dictobj.py
cryptopian_infra/utils/dictutils.py
cryptopian_infra/utils/listutils.py
cryptopian_infra/utils/mathutils.py
cryptopian_infra-0.2.2.dist-info/licenses/LICENSE
cryptopian_infra-0.2.2.dist-info/METADATA
cryptopian_infra-0.2.2.dist-info/WHEEL
cryptopian_infra-0.2.2.dist-info/top_level.txt
cryptopian_infra-0.2.2.dist-info/RECORD
