Metadata-Version: 2.4
Name: cryptopian_infra
Version: 0.2.2
Summary: Cryptopian Infrastructure Library
Author-email: Han Wu <xjohnwu@gmail.com>
Project-URL: Source, https://github.com/Cryptopian001/cryptopian_infrastructure_python
Project-URL: Homepage, https://github.com/Cryptopian001/cryptopian_infrastructure_python
Project-URL: Issues, https://github.com/Cryptopian001/cryptopian_infrastructure_python/issues
Classifier: Programming Language :: Python :: 3
Classifier: License :: OSI Approved :: MIT License
Classifier: Operating System :: OS Independent
Requires-Python: >=3.11
License-File: LICENSE
Requires-Dist: influxdb
Requires-Dist: influxdb_client
Requires-Dist: jsmin
Requires-Dist: onepasswordconnectsdk
Requires-Dist: pandas
Requires-Dist: pymongo
Requires-Dist: python-dotenv
Requires-Dist: requests
Provides-Extra: dev
Requires-Dist: pytest>=8.3.3; extra == "dev"
Requires-Dist: pytest-asyncio; extra == "dev"
Requires-Dist: pip-tools; extra == "dev"
Dynamic: license-file
